client/__init__.py
client/client.py
management_client-0.0.2.dist-info/LICENSE.txt
management_client-0.0.2.dist-info/METADATA
management_client-0.0.2.dist-info/WHEEL
management_client-0.0.2.dist-info/top_level.txt
management_client-0.0.2.dist-info/RECORD
